visdax/__init__.py
visdax/client.py
visdax-0.2.13.dist-info/METADATA
visdax-0.2.13.dist-info/WHEEL
visdax-0.2.13.dist-info/top_level.txt
visdax-0.2.13.dist-info/RECORD
