Metadata-Version: 2.4
Name: visdax
Version: 0.2.13
Summary: B2B High-Fidelity Vision Restoration SDK with Compulsory Vault Caching
Author-email: Sourabh Yadav <sourabh@visdax.com>
Project-URL: Homepage, https://visdax.com
Classifier: Programming Language :: Python :: 3
Classifier: License :: OSI Approved :: MIT License
Classifier: Operating System :: OS Independent
Requires-Python: >=3.10
Requires-Dist: requests>=2.28.0
Requires-Dist: pqdm>=0.2.0
